setup.py
ziptests/__init__.py
ziptests/tests.py
ziptests.egg-info/PKG-INFO
ziptests.egg-info/SOURCES.txt
ziptests.egg-info/dependency_links.txt
ziptests.egg-info/top_level.txt