Metadata-Version: 1.0
Name: ziptests
Version: 1.0.0
Summary: ['Programming Language :: Python']
Home-page: http://www.osforce.com
Author: liuhang
Author-email: liuhang-2005@163.com
License: MIT
Keywords: framework zip testing
Platform: any
